{"baseInfo": {"productName": "鲜梅", "productCode": "0809400001", "productCodeStatus": "正常", "productUpdateTime": "2019/4/3 18:24:40"}, "taxRateInfo": {"productUnitOfMeasurement": "千克", "productExportTariffRate": "0%", "productExportTaxRebateRate": "6%", "productExportTemporaryTaxRate": "", "productExportVATRate": "9%", "productExportImportPreferentialTaxRate": "10%", "productImportTemporaryTaxRate": "/", "productImportCommonTaxRate": "70%", "productConsumptionTaxRate": "-"}, "elementDeclar": {"productElementsOfDeclaration": ["品牌类型 [?]", "出口享惠情况 [?]", "制作或保存方法[鲜]", "等级", "GTIN", "CAS"]}, "regulCondition": {"productRegulationConditions": ["入境货物通关单", "出境货物通关单"]}, "inspAndQuartCate": {"productInspectionAndQuarantineCategories": ["进口食品卫生监督检验", "出口食品卫生监督检验", "进境动植物、动植物产品检疫", "出境动植物、动植物产品检疫"]}, "chapters": {"chapters": [{"code": "第2类", "name": "植物产品"}, {"code": "08", "name": "食用水果及坚果;柑桔属水果或甜瓜的果皮"}, {"code": "0809", "name": "鲜的杏、樱桃、桃(包括油桃)、梅及李:"}, {"code": "08094000", "name": "梅及李"}]}, "ciq": {"code": "0809400001999", "name": "鲜梅"}, "naviHtmls": [{"name": "上一条:0809300000-鲜桃,包括鲜油桃", "link": "https://www.hsbianma.com/Code/0809300000.html"}, {"name": "下一条:0809400090-鲜李子", "link": "https://www.hsbianma.com/Code/0809400090.html"}]}