{"baseInfo": {"productName": "已磨的姜", "productCode": "0910120000", "productCodeStatus": "正常", "productUpdateTime": "2019/4/3 18:25:05"}, "taxRateInfo": {"productUnitOfMeasurement": "千克", "productExportTariffRate": "0%", "productExportTaxRebateRate": "6%", "productExportTemporaryTaxRate": "", "productExportVATRate": "9%", "productExportImportPreferentialTaxRate": "15%", "productImportTemporaryTaxRate": "/", "productImportCommonTaxRate": "50%", "productConsumptionTaxRate": "-"}, "elementDeclar": {"productElementsOfDeclaration": ["品牌类型 [?]", "出口享惠情况 [?]", "加工方法[未磨、已磨]", "GTIN", "CAS"]}, "regulCondition": {"productRegulationConditions": ["入境货物通关单", "出境货物通关单"]}, "inspAndQuartCate": {"productInspectionAndQuarantineCategories": ["进口食品卫生监督检验", "出口食品卫生监督检验", "进境动植物、动植物产品检疫", "出境动植物、动植物产品检疫"]}, "chapters": {"chapters": [{"code": "第2类", "name": "植物产品"}, {"code": "09", "name": "咖啡、茶、马黛茶及调味香料"}, {"code": "0910", "name": "姜、番红花、姜黄、麝香草、月桂叶、咖喱及其他调味香料:"}, {"code": "09101", "name": "姜:"}, {"code": "09101200", "name": "已磨"}]}, "ciq": {"code": "0910120000102", "name": "已磨的姜(调味料)"}, "naviHtmls": [{"name": "上一条:0910110000-未磨的姜", "link": "https://www.hsbianma.com/Code/0910110000.html"}, {"name": "下一条:0910200000-番红花", "link": "https://www.hsbianma.com/Code/0910200000.html"}]}