{"baseInfo": {"productName": "牛黄", "productCode": "0510001010", "productCodeStatus": "正常", "productUpdateTime": "2019/4/3 18:23:23"}, "taxRateInfo": {"productUnitOfMeasurement": "千克", "productExportTariffRate": "0%", "productExportTaxRebateRate": "6%", "productExportTemporaryTaxRate": "", "productExportVATRate": "9%", "productExportImportPreferentialTaxRate": "3%", "productImportTemporaryTaxRate": "/", "productImportCommonTaxRate": "14%", "productConsumptionTaxRate": "-"}, "elementDeclar": {"productElementsOfDeclaration": ["品牌类型 [?]", "出口享惠情况 [?]", "制作或保存方法[鲜、冷、冻、干或用其他方法暂时保藏]", "GTIN", "CAS"]}, "regulCondition": {"productRegulationConditions": ["禁止出口商品", "入境货物通关单"]}, "inspAndQuartCate": {"productInspectionAndQuarantineCategories": ["进境动植物、动植物产品检疫", "出境动植物、动植物产品检疫"]}, "chapters": {"chapters": [{"code": "第1类", "name": "活动物;动物产品"}, {"code": "05", "name": "其他动物产品"}, {"code": "0510", "name": "龙涎香、海狸香、灵猫香及麝香;斑蝥;胆汁,不论是否干制;供配制药用的腺体及其他动物产品,鲜、冷、冻或用其他方法暂时保藏的:"}, {"code": "05100010", "name": "黄药"}]}, "ciq": {"code": "0510001010103", "name": "牛黄(药用体外培育牛黄)"}, "naviHtmls": [{"name": "上一条:0508009090-其他水产品的壳、骨", "link": "https://www.hsbianma.com/Code/0508009090.html"}, {"name": "下一条:0510001020-猴枣", "link": "https://www.hsbianma.com/Code/0510001020.html"}]}